pretix_venueless/__init__.py
pretix_venueless/apps.py
pretix_venueless/signals.py
pretix_venueless/urls.py
pretix_venueless/views.py
pretix_venueless/locale/django.pot
pretix_venueless/locale/ar/LC_MESSAGES/django.mo
pretix_venueless/locale/ar/LC_MESSAGES/django.po
pretix_venueless/locale/de/LC_MESSAGES/django.mo
pretix_venueless/locale/de/LC_MESSAGES/django.po
pretix_venueless/locale/de_Informal/.gitkeep
pretix_venueless/locale/de_Informal/LC_MESSAGES/django.mo
pretix_venueless/locale/de_Informal/LC_MESSAGES/django.po
pretix_venueless/locale/fi/LC_MESSAGES/django.mo
pretix_venueless/locale/fi/LC_MESSAGES/django.po
pretix_venueless/locale/hr/LC_MESSAGES/django.mo
pretix_venueless/locale/hr/LC_MESSAGES/django.po
pretix_venueless/locale/ja/LC_MESSAGES/django.mo
pretix_venueless/locale/ja/LC_MESSAGES/django.po
pretix_venueless/locale/nl/LC_MESSAGES/django.mo
pretix_venueless/locale/nl/LC_MESSAGES/django.po
pretix_venueless/locale/nl_Informal/LC_MESSAGES/django.mo
pretix_venueless/locale/nl_Informal/LC_MESSAGES/django.po
pretix_venueless/locale/pt_PT/LC_MESSAGES/django.mo
pretix_venueless/locale/pt_PT/LC_MESSAGES/django.po
pretix_venueless/static/pretix_venueless/.gitkeep
pretix_venueless/static/pretix_venueless/logo.svg
pretix_venueless/templates/pretix_venueless/.gitkeep
pretix_venueless/templates/pretix_venueless/order_info.html
pretix_venueless/templates/pretix_venueless/settings.html
pretix_venueless-1.3.1.dist-info/LICENSE
pretix_venueless-1.3.1.dist-info/METADATA
pretix_venueless-1.3.1.dist-info/WHEEL
pretix_venueless-1.3.1.dist-info/entry_points.txt
pretix_venueless-1.3.1.dist-info/top_level.txt
pretix_venueless-1.3.1.dist-info/RECORD
