Metadata-Version: 2.1
Name: pretix-venueless
Version: 1.3.1
Summary: Integrates pretix with venueless.org
Author-email: pretix team <support@pretix.eu>
Maintainer-email: pretix team <support@pretix.eu>
License: 
Project-URL: homepage, https://github.com/pretix/pretix-venueless
Keywords: pretix
Requires-Python: >=3.9
License-File: LICENSE
Requires-Dist: PyJWT
